<?xml version="1.0" encoding="UTF-8"?>
<flashcard>
	<term>
		<![CDATA[
			<p>Les phrases suivantes contiennent-elles des tournures passives? Expliquez votre r&eacute;ponse.</p>
			<p>&nbsp;</p>
			<p>La femme de ménage <strong>a été congédiée</strong> par la maîtresse de maison.</p>
			<p>a) (Oui/Non)</p>
			<p>b) ____________________</p>
		]]>
	</term>

	<definition>
		<![CDATA[
			<br />
			<p>La femme de ménage <strong>a été congédiée</strong> par la maîtresse de maison.</p>
			<p class="orange">a) Oui</p>
			<p class="orange">b) Le sujet grammatical, la femme de ménage subit l'action. C'est la maîtresse de maison qui a congédié la femme de ménage. La maîtresse de maison est le complément d'agent dans la phrase au passif.</p>
		]]>
	</definition>
	
	<sidebar></sidebar>
</flashcard>
